django_markwhat_next/__init__.py
django_markwhat_next/models.py
django_markwhat_next/tests.py
django_markwhat_next/templatetags/__init__.py
django_markwhat_next/templatetags/markup.py
django_markwhat_next-1.7.0.dist-info/AUTHORS.rst
django_markwhat_next-1.7.0.dist-info/LICENSE
django_markwhat_next-1.7.0.dist-info/METADATA
django_markwhat_next-1.7.0.dist-info/WHEEL
django_markwhat_next-1.7.0.dist-info/top_level.txt
django_markwhat_next-1.7.0.dist-info/RECORD
