Metadata-Version: 2.1
Name: django-markwhat-next
Version: 1.7.0
Summary: A collection of template filters that implement common markup languages.
Home-page: https://pypi.org/project/django-markwhat/
Author: Alireza Savand & Ron Friedman
Author-email: alireza.savand@gmail.com, rfriedman@lanets.ca
License: BSD-3-Clause
Keywords: django,markdown,markup,textile,rst,reStructuredText,docutils,commonmark,web
Platform: OS Independent
Classifier: Development Status :: 5 - Production/Stable
Classifier: Development Status :: 6 - Mature
Classifier: Environment :: Web Environment
Classifier: Framework :: Django
Classifier: Intended Audience :: Developers
Classifier: License :: OSI Approved :: BSD License
Classifier: Operating System :: OS Independent
Classifier: Programming Language :: Python
Classifier: Programming Language :: Python :: 2
Classifier: Programming Language :: Python :: 2.7
Classifier: Programming Language :: Python :: 3
Classifier: Programming Language :: Python :: 3.4
Classifier: Programming Language :: Python :: 3.5
Classifier: Programming Language :: Python :: 3.6
Classifier: Topic :: Software Development
Classifier: Topic :: Software Development :: Libraries
License-File: LICENSE
License-File: AUTHORS.rst
Requires-Dist: Django
